calcalc/CalCalc.py
calcalc/__init__.py
calcalc/test/__init__.py
calcalc/test/test.py
hw_3-0.0.4.dist-info/METADATA
hw_3-0.0.4.dist-info/WHEEL
hw_3-0.0.4.dist-info/top_level.txt
hw_3-0.0.4.dist-info/RECORD
